shapesinc/__info__.py
shapesinc/__init__.py
shapesinc/abc.py
shapesinc/http.py
shapesinc/shape.py
shapesinc-0.3.4.dist-info/licenses/LICENSE
shapesinc-0.3.4.dist-info/METADATA
shapesinc-0.3.4.dist-info/WHEEL
shapesinc-0.3.4.dist-info/top_level.txt
shapesinc-0.3.4.dist-info/RECORD
