Metadata-Version: 2.4
Name: shapesinc
Version: 0.3.4
Summary: A module for interacting with shapes.inc API.
Home-page: https://github.com/Rishiraj0100/shapesinc-py
Author: Rishiraj0100
License: MIT
Project-URL: Documentation, https://shapesinc-py.rtfd.io/
Project-URL: Issue tracker, https://github.com/Rishiraj0100/shapesinc-py/issues
Classifier: Programming Language :: Python :: 3
Classifier: License :: OSI Approved :: MIT License
Classifier: Operating System :: OS Independent
Requires-Python: >=3.8
License-File: LICENSE
Requires-Dist: aiohttp
Dynamic: author
Dynamic: classifier
Dynamic: description
Dynamic: description-content-type
Dynamic: home-page
Dynamic: license
Dynamic: license-file
Dynamic: project-url
Dynamic: requires-dist
Dynamic: requires-python
Dynamic: summary
